{"apidoc_index.md":"clXxztnd","aps_index.md":"BEp9NZ5z","config_index.md":"Dr8sipZB","config_other_mrc.md":"CzPUaUOn","config_other_srpc.md":"xlLquqwq","config_slardar_login.md":"DstV-EUs","config_slardar_mfa.md":"YTPFJT70","config_slardar_other.md":"C7xyfWVL","config_slardar_sso.md":"xDIM3Y1y","config_slardar_token.md":"BbN1q9yE","config_sorm_ds.md":"CXfIhqT2","config_sorm_setting.md":"CS26nABH","config_starter_app.md":"BK9OspKz","config_starter_javalin.md":"B0XrfKiX","config_starter_vertx.md":"VHSZOJsu","guide_misc_event.md":"BdJljrXt","guide_misc_timer.md":"CISKxCR-","guide_pre-require.md":"DjrpFnB9","guide_quickstart.md":"Bqrlga1i","guide_remote_intro.md":"DUzDhhSq","guide_remote_mrc.md":"CgvC1h_1","guide_remote_srpc.md":"DQei2YfQ","guide_slardar_intro.md":"YyKOjSDq","guide_slardar_spi.md":"OcVJ1y9G","guide_slardar_sso.md":"Dyudxlv9","guide_sorm_entity.md":"BjWiqPaM","guide_sorm_intro.md":"Dq-X5PqP","guide_sorm_multi.md":"Dsx4Lozw","guide_sorm_postgis.md":"CT994KM4","guide_starter_app.md":"B-q3hLUg","guide_starter_cloud.md":"-lDumsyK","guide_starter_next.md":"CadSDjiI","guide_starter_tongweb.md":"ChEPU5Ux","guide_starter_undertow.md":"DFrIedl2","guide_version.md":"B2o9V3PQ","index.md":"BR5BTrOt","posts_index.md":"Ck1r-0Ua","posts_p-docker-run.md":"D5zgAOIr","posts_p-java-design-patterns.md":"dolM5-kp","posts_p-java-restart.md":"NAh3U6tH","posts_p-java-spi.md":"Bkl5eCWK","posts_p-java-stw.md":"dj6DIuf8","posts_p-java-volatile.md":"Csmy8GEx","posts_p-linux-version.md":"DeTzqc6Y","posts_p-maven-offline.md":"XlCUWhWG","posts_p-ms-work.md":"DWi6bgKW","posts_p-naocs-auth.md":"D1ZP2eCr","posts_p-paradedb-1.md":"CBnJCbGD","posts_p-pg-ext.md":"DuKnDOm8","posts_p-postgis-version.md":"CRw7wai5","posts_p-ratelimit.md":"C-rFibd-","posts_p-security-dos.md":"OdFgyk2m","posts_p-sedona-1.md":"CgeM56KY","posts_p-singleton.md":"BaDhclUY","posts_p-solid.md":"DBqusG0c","posts_p-sql.md":"BKq0oNw3"}
